.coveragerc
.git-pre-commit
.gitignore
CREDITS
HISTORY.rst
LICENSE
MANIFEST.in
Makefile
README.rst
make.bat
setup.cfg
setup.py
tox.ini
demo/anti_flood_ftpd.py
demo/basic_ftpd.py
demo/keycert.pem
demo/md5_ftpd.py
demo/multi_proc_ftp.py
demo/multi_thread_ftp.py
demo/throttled_ftpd.py
demo/tls_ftpd.py
demo/unix_daemon.py
demo/unix_ftpd.py
demo/winnt_ftpd.py
docs/Makefile
docs/README
docs/adoptions.rst
docs/api.rst
docs/benchmarks.rst
docs/conf.py
docs/faqs.rst
docs/index.rst
docs/install.rst
docs/make.bat
docs/rfc-compliance.rst
docs/tutorial.rst
docs/images/freebsd.gif
pyftpdlib/__init__.py
pyftpdlib/__main__.py
pyftpdlib/_compat.py
pyftpdlib/authorizers.py
pyftpdlib/filesystems.py
pyftpdlib/handlers.py
pyftpdlib/ioloop.py
pyftpdlib/log.py
pyftpdlib/prefork.py
pyftpdlib/servers.py
pyftpdlib/test/README
pyftpdlib/test/__init__.py
pyftpdlib/test/__main__.py
pyftpdlib/test/keycert.pem
pyftpdlib/test/runner.py
pyftpdlib/test/test_authorizers.py
pyftpdlib/test/test_filesystems.py
pyftpdlib/test/test_functional.py
pyftpdlib/test/test_functional_ssl.py
pyftpdlib/test/test_ioloop.py
pyftpdlib/test/test_misc.py
pyftpdlib/test/test_servers.py
pyftplib.egg-info/PKG-INFO
pyftplib.egg-info/SOURCES.txt
pyftplib.egg-info/dependency_links.txt
pyftplib.egg-info/requires.txt
pyftplib.egg-info/top_level.txt
scripts/ftpbench
scripts/generate_manifest.py
scripts/print_announce.py