Metadata-Version: 2.1
Name: pyftplib
Version: 1.5.6
Summary: Very fast asynchronous FTP server library
Home-page: https://github.com/giampaolo/pyftpdlib/
Author: Giampaolo Rodola'
Author-email: g.rodola@gmail.com
License: MIT
Keywords: ftp,ftps,server,ftpd,daemon,python,ssl,sendfile,asynchronous,nonblocking,eventdriven,rfc959,rfc1123,rfc2228,rfc2428,rfc2640,rfc3659
Platform: Platform Independent
Classifier: Development Status :: 5 - Production/Stable
Classifier: Environment :: Console
Classifier: Intended Audience :: Developers
Classifier: Intended Audience :: System Administrators
Classifier: License :: OSI Approved :: MIT License
Classifier: Operating System :: OS Independent
Classifier: Programming Language :: Python
Classifier: Topic :: Internet :: File Transfer Protocol (FTP)
Classifier: Topic :: Software Development :: Libraries :: Python Modules
Classifier: Topic :: System :: Filesystems
Classifier: Programming Language :: Python
Classifier: Programming Language :: Python :: 2
Classifier: Programming Language :: Python :: 2.6
Classifier: Programming Language :: Python :: 2.7
Classifier: Programming Language :: Python :: 3
Classifier: Programming Language :: Python :: 3.4
Classifier: Programming Language :: Python :: 3.5
Classifier: Programming Language :: Python :: 3.6
Provides-Extra: ssl
